<?xml version="1.0" encoding="utf-8" ?>
<dwsync>
<file name="2_02.gif" local="131171868000000000" remote="131171868000000000" testing="0" />
<file name="60-Day-Guarantee-Seal.png" local="131202108000000000" remote="131202108000000000" testing="0" />
<file name="About-AdoraDeal-2.gif" local="131171868000000000" remote="131171868000000000" testing="0" />
<file name="About-AdoraDeal.gif" local="131171868000000000" remote="131171868000000000" testing="0" />
<file name="About-Linux-Computers-2.gif" local="131171868000000000" remote="131171868000000000" testing="0" />
<file name="About-Linux-Computers.gif" local="131171868000000000" remote="131171868000000000" testing="0" />
<file name="AdoraDeal-Amazon-Store-2.gif" local="130807260000000000" remote="130807260000000000" testing="0" />
<file name="AdoraDeal-Amazon-Store.gif" local="130807260000000000" remote="130807260000000000" testing="0" />
<file name="AdoraDeal-Bonanza-Store-11.gif" local="131171868000000000" remote="131171868000000000" testing="0" />
<file name="AdoraDeal-Bonanza-Store-22.gif" local="131171868000000000" remote="131171868000000000" testing="0" />
<file name="AdoraDeal-Logo-150x100.gif" local="130578300000000000" remote="130578300000000000" testing="0" />
<file name="AdoraDeal-Logo-151x90.gif" local="130578300000000000" remote="130578300000000000" testing="0" />
<file name="AdoraDeal-Logo-Plus-Leaf.png" local="131202972000000000" remote="131202972000000000" testing="0" />
<file name="AdoraDeal-bonanza-Store-22.gif" local="131171868000000000" remote="131171868000000000" testing="0" />
<file name="AdoraDeal-eBay-Store-11.gif" local="131171868000000000" remote="131171868000000000" testing="0" />
<file name="AdoraDeal-eBay-Store-2.gif" local="130807260000000000" remote="130807260000000000" testing="0" />
<file name="AdoraDeal-eBay-Store-22.gif" local="131171868000000000" remote="131171868000000000" testing="0" />
<file name="AdoraDeal-eBay-Store.gif" local="130807260000000000" remote="130807260000000000" testing="0" />
<file name="AdoraDeal-eCRATER-Store-2.gif" local="130807260000000000" remote="130807260000000000" testing="0" />
<file name="AdoraDeal-eCRATER-Store.gif" local="130807260000000000" remote="130807260000000000" testing="0" />
<file name="AdoraDeal_Logo.gif" local="131171868000000000" remote="131171868000000000" testing="0" />
<file name="Background-Left-1.gif" local="131171868000000000" remote="131171868000000000" testing="0" />
<file name="Background-Left-11.gif" local="131171868000000000" remote="131171868000000000" testing="0" />
<file name="Background-Left-2.gif" local="131171868000000000" remote="131171868000000000" testing="0" />
<file name="Background-Left-3.gif" local="131171868000000000" remote="131171868000000000" testing="0" />
<file name="Background-Right-1.gif" local="131171868000000000" remote="131171868000000000" testing="0" />
<file name="Background-Right-11.gif" local="131171868000000000" remote="131171868000000000" testing="0" />
<file name="Background-Right-2.gif" local="131171868000000000" remote="131171868000000000" testing="0" />
<file name="Background-Right-3.gif" local="131171868000000000" remote="131171868000000000" testing="0" />
<file name="CC-icons.png" local="131202108000000000" remote="131202108000000000" testing="0" />
<file name="Code-AdoraDeal-2.gif" local="131171868000000000" remote="131171868000000000" testing="0" />
<file name="Code-AdoraDeal.gif" local="131171868000000000" remote="131171868000000000" testing="0" />
<file name="Contact-AdoraDeal-2.gif" local="131171868000000000" remote="131171868000000000" testing="0" />
<file name="Contact-AdoraDeal.gif" local="131171868000000000" remote="131171868000000000" testing="0" />
<file name="Divider-Text-Bottom.gif" local="131171868000000000" remote="131171868000000000" testing="0" />
<file name="Divider-Text-Bottom2.gif" local="131171868000000000" remote="131171868000000000" testing="0" />
<file name="Divider-Text-Top.gif" local="131171868000000000" remote="131171868000000000" testing="0" />
<file name="Home-AdoraDeal-2.gif" local="131171868000000000" remote="131171868000000000" testing="0" />
<file name="Home-AdoraDeal.gif" local="131171868000000000" remote="131171868000000000" testing="0" />
<file name="Open-Invention-Network-Logo.png" local="131182236000000000" remote="131182236000000000" testing="0" />
<file name="Open-Invention-Network.png" local="131202108000000000" remote="131202108000000000" testing="0" />
<file name="PayPal-verification_seal.gif" local="130578300000000000" remote="130578300000000000" testing="0" />
<file name="Privacy-AdoraDeal-2.gif" local="130578300000000000" remote="130578300000000000" testing="0" />
<file name="Privacy-AdoraDeal.gif" local="130578300000000000" remote="130578300000000000" testing="0" />
<file name="Products-AdoraDeal-2.gif" local="131171868000000000" remote="131171868000000000" testing="0" />
<file name="Products-AdoraDeal.gif" local="131171868000000000" remote="131171868000000000" testing="0" />
<file name="Screenshot-AdoraDeal-Debian-Linux.png" local="131209020000000000" remote="131209020000000000" testing="0" />
<file name="Screenshot-AdoraDeal-Laptop.png" local="131209884000000000" remote="131209884000000000" testing="0" />
<file name="Terms-AdoraDeal-2.gif" local="130578300000000000" remote="130578300000000000" testing="0" />
<file name="Terms-AdoraDeal.gif" local="130578300000000000" remote="130578300000000000" testing="0" />
<file name="ambiance-background.png" local="131243580000000000" remote="131243580000000000" testing="0" />
<file name="background-full-width.gif" local="131171868000000000" remote="131171868000000000" testing="0" />
<file name="comodo_secure_seal.png" local="131461308000000000" remote="131461308000000000" testing="0" />
<file name="comodo_secure_seal_100x85_transp.png" local="131171868000000000" remote="131171868000000000" testing="0" />
<file name="comodo_secure_seal_113x59_transp.png" local="131171868000000000" remote="131171868000000000" testing="0" />
<file name="divider1.gif" local="131171868000000000" remote="131171868000000000" testing="0" />
<file name="email-2.png" local="131189148000000000" remote="131189148000000000" testing="0" />
<file name="favicon.ico" local="130274172000000000" remote="130274172000000000" testing="0" />
<file name="favicon.png" local="131183964000000000" remote="131183964000000000" testing="0" />
<file name="home-page_15.gif" local="131171868000000000" remote="131171868000000000" testing="0" />
<file name="image-235.gif" local="131171868000000000" remote="131171868000000000" testing="0" />
<file name="image-contact2.png" local="131196060000000000" remote="131196060000000000" testing="0" />
<file name="space.gif" local="131171868000000000" remote="131171868000000000" testing="0" />
<file name="test-home-page.gif" local="130265532000000000" remote="130265532000000000" testing="0" />
<file name="test-home-page2.gif" local="130268124000000000" remote="130268124000000000" testing="0" />
<file name="test-home-page3.gif" local="130283676000000000" remote="130283676000000000" testing="0" />
</dwsync>